<?xml version="1.0" encoding="UTF-8"?>
<!DOCTYPE tv SYSTEM "xmltv.dtd">

<tv generator-info-name="epg2xml 1.5.2">
  <channel id="Tokyo MX">
    <display-name>TOKYO MX</display-name>
    <icon src="https://upload.wikimedia.org/wikipedia/commons/thumb/6/6f/Tokyo_metropolitan_television_logo_%28rainbow%29.svg/300px-Tokyo_metropolitan_television_logo_%28rainbow%29.svg.png" />
  </channel>
  <channel id="Animax.id">
    <display-name>Animax ID</display-name>
    <icon src="https://static.epg.best/id/Animax.id.png" />
  </channel>
  <channel id="Asahi.jp">
    <display-name>TV ASAHI</display-name>
    <icon src="https://upload.wikimedia.org/wikipedia/commons/thumb/5/51/TV_Asahi_Logo.svg/150px-TV_Asahi_Logo.svg.png" />
  </channel>
  <channel id="eTele.jp">
    <display-name>NHK E</display-name>
    <icon src="https://upload.wikimedia.org/wikipedia/commons/thumb/a/aa/NHKE%E3%83%86%E3%83%AC%E3%83%AD%E3%82%B42020-.png/150px-NHKE%E3%83%86%E3%83%AC%E3%83%AD%E3%82%B42020-.png" />
  </channel>
  <channel id="FujiTV.jp">
    <display-name>Fuji TV</display-name>
    <icon src="https://upload.wikimedia.org/wikipedia/en/thumb/e/e9/Fuji_TV_logo.svg/150px-Fuji_TV_logo.svg.png" />
  </channel>
  <channel id="NHK1Tokyo.jp">
    <display-name>NHK G</display-name>
    <icon src="https://upload.wikimedia.org/wikipedia/commons/thumb/6/6f/NHK%E7%B7%8F%E5%90%88%E3%83%AD%E3%82%B42020-.png/150px-NHK%E7%B7%8F%E5%90%88%E3%83%AD%E3%82%B42020-.png" />
  </channel>
  <channel id="NipponTV.jp">
    <display-name>NTV</display-name>
    <icon src="https://upload.wikimedia.org/wikipedia/commons/thumb/5/5e/Nippon_TV_logo_2014.svg/150px-Nippon_TV_logo_2014.svg.png" />
  </channel>
  <channel id="TBS2.jp">
    <display-name>TBS</display-name>
    <icon src="https://upload.wikimedia.org/wikipedia/commons/thumb/1/14/Tokyo_Broadcasting_System_logo_2020.svg/150px-Tokyo_Broadcasting_System_logo_2020.svg.png" />
  </channel>
  <channel id="TVTokyo.jp">
    <display-name>TV Tokyo</display-name>
    <icon src="https://upload.wikimedia.org/wikipedia/commons/thumb/b/b7/TV_Tokyo_logo_20110629.svg/150px-TV_Tokyo_logo_20110629.svg.png" />
  </channel>
  <channel id="FujiNext.jp">
    <display-name>Fuji_Next</display-name>
    <icon src="https://static.epg.best/jp/FujiNext.jp.png" />
  </channel>
  <channel id="FujiOne.jp">
    <display-name>Fuji_One</display-name>
    <icon src="https://static.epg.best/jp/FujiOne.jp.png" />
  </channel>
  <channel id="FujiTwo.jp">
    <display-name>Fuji_Two</display-name>
    <icon src="https://static.epg.best/jp/FujiTwo.jp.png" />
  </channel>
  <channel id="mnet.jp">
    <display-name>mnet-japan</display-name>
    <icon src="https://asianwiki.com/images/6/63/Mnet-p1.png" />
  </channel>
  <channel id="kbsworld.jp">
    <display-name>kbs-world</display-name>
    <icon src="https://www.hikaritv.net/resources/hikari/pc/images/ch_logo/ch854/552.png" />
  </channel>
  <channel id="ANIMAX.jp">
    <display-name>ANIMAX</display-name>
    <icon src="https://image.pngaaa.com/303/1608303-middle.png" />
  </channel>
  
</tv>